art/__init__.py
art/__main__.py
art/_cache.py
art/_config.py
art/_gitlab.py
art/_install.py
art/_oauth.py
art/_paths.py
art/_termui.py
art/_yaml.py
art/command_line.py
gitlab_art-0.5.0.dist-info/licenses/COPYING
gitlab_art-0.5.0.dist-info/METADATA
gitlab_art-0.5.0.dist-info/WHEEL
gitlab_art-0.5.0.dist-info/entry_points.txt
gitlab_art-0.5.0.dist-info/top_level.txt
gitlab_art-0.5.0.dist-info/RECORD
