Metadata-Version: 2.4
Name: gitlab-art
Version: 0.5.0
Summary: Gitlab artifact manager
Home-page: https://github.com/kosma/gitlab-art
Author: Kosma Moczek
Author-email: kosma@kosma.pl
License: WTFPL
Requires-Python: >=3.7
License-File: COPYING
Requires-Dist: PyYAML
Requires-Dist: platformdirs
Requires-Dist: click
Requires-Dist: python-gitlab>=3.12.0
Dynamic: author
Dynamic: author-email
Dynamic: description
Dynamic: description-content-type
Dynamic: home-page
Dynamic: license
Dynamic: license-file
Dynamic: requires-dist
Dynamic: requires-python
Dynamic: summary
